README.rst
setup.py
iob/__init__.py
iob/base.py
iob/error.py
iob/request.py
iob/response.py
iob.egg-info/PKG-INFO
iob.egg-info/SOURCES.txt
iob.egg-info/dependency_links.txt
iob.egg-info/requires.txt
iob.egg-info/top_level.txt
script/__init__.py
script/demo.py
script/test.py
test/__init__.py
test/basic.py
test/handler.py
test/request.py
test/response.py
test/task_generator.py