Metadata-Version: 1.1
Name: iob
Version: 0.0.2
Summary: Site Scraping Framework based on py3 asyncio
Home-page: UNKNOWN
Author: Gregory Petukhov
Author-email: lorien@lorien.name
License: MIT
Platform: UNKNOWN
Classifier: Programming Language :: Python
Classifier: Programming Language :: Python :: 3.4
Classifier: Programming Language :: Python :: Implementation :: CPython
Classifier: License :: OSI Approved :: MIT License
Classifier: Topic :: Software Development :: Libraries :: Application Frameworks
Classifier: Topic :: Software Development :: Libraries :: Python Modules
Classifier: Topic :: Internet :: WWW/HTTP
